daybetter_led_strip/__init__.py
daybetter_led_strip/const.py
daybetter_led_strip/led_strip.py
daybetter_led_strip/util.py
daybetter_led_strip-0.3.0.dist-info/licenses/LICENSE
daybetter_led_strip-0.3.0.dist-info/METADATA
daybetter_led_strip-0.3.0.dist-info/WHEEL
daybetter_led_strip-0.3.0.dist-info/top_level.txt
daybetter_led_strip-0.3.0.dist-info/RECORD
