Metadata-Version: 2.4
Name: daybetter-led-strip
Version: 0.3.0
Summary: Control Daybetter RGB LED strips over BLE
Author-email: Siddhant Kameswar <61r7jw39@kameswar.com>
License-Expression: MIT
Project-URL: Homepage, https://github.com/grimsteel/daybetter-led-strip
Project-URL: Issues, https://github.com/grimsteel/daybetter-led-strip/issues
License-File: LICENSE
Requires-Dist: bleak
Requires-Dist: bleak-retry-connector
Dynamic: license-file
